{"inputs":[{"name":".clientdata_output_app-hot_height","timestamp":"2024-02-20 16:39:19.972-0500","value":700.0001,"type":"","binding":""},{"name":".clientdata_output_app-hot_height","timestamp":"2024-02-20 16:39:19.949-0500","value":700.0001,"type":"","binding":""},{"name":".clientdata_output_app-hot_width","timestamp":"2024-02-20 16:39:19.972-0500","value":3000.0002,"type":"","binding":""},{"name":".clientdata_output_app-hot_width","timestamp":"2024-02-20 16:39:19.949-0500","value":3000.0002,"type":"","binding":""},{"name":"HandsontableCopyPaste","timestamp":"2024-02-20 16:39:19.937-0500","value":" ","type":"","binding":"shiny.textareaInput"}],"session":[{"app":"police-maintenance","user":"asadowsk","server_connected":"2024-02-20 16:39:19.846-0500","sessionid":"810722d0e9e33b10161085277a46e55b","server_disconnected":"2024-02-20 16:39:24.829-0500","user_agent":"Mozilla/5.0 (Windows NT 10.0; Win64; x64) AppleWebKit/537.36 (KHTML, like Gecko) Chrome/121.0.0.0 Safari/537.36 Edg/121.0.0.0","screen_res":"2560x1440","browser_res":"1996x1017","pixel_ratio":0.9,"browser_connected":"2024-02-20 16:39:19.934-0500"}]}
