{"inputs":[{"name":".clientdata_output_app-hot_width","timestamp":"2024-02-20 15:30:24.262-0500","value":3000,"type":"","binding":""},{"name":"HandsontableCopyPaste","timestamp":"2024-02-20 15:30:24.253-0500","value":" ","type":"","binding":"shiny.textareaInput"},{"name":".clientdata_output_app-hot_height","timestamp":"2024-02-20 15:30:24.262-0500","value":700,"type":"","binding":""}],"session":[{"app":"police-maintenance","user":"asadowsk","server_connected":"2024-02-20 15:30:24.148-0500","sessionid":"aa8e0da86b2c3f9e855896c414754d60","server_disconnected":"2024-02-20 15:38:46.340-0500","user_agent":"Mozilla/5.0 (Windows NT 10.0; Win64; x64) AppleWebKit/537.36 (KHTML, like Gecko) RStudio/2023.06.1+524 Chrome/110.0.5481.208 Electron/23.3.0 Safari/537.36","screen_res":"2560x1440","browser_res":"1066x531","pixel_ratio":1.25,"browser_connected":"2024-02-20 15:30:24.251-0500"}]}
