{"inputs":[{"name":".clientdata_pixelratio","timestamp":"2024-02-21 08:54:37.213-0500","value":1.25,"type":"","binding":""},{"name":".clientdata_pixelratio","timestamp":"2024-02-21 08:54:37.150-0500","value":1.25,"type":"","binding":""},{"name":".clientdata_pixelratio","timestamp":"2024-02-21 08:54:39.059-0500","value":1.25,"type":"","binding":""},{"name":".clientdata_pixelratio","timestamp":"2024-02-21 08:54:39.125-0500","value":1.25,"type":"","binding":""},{"name":".clientdata_pixelratio","timestamp":"2024-02-21 08:54:37.179-0500","value":1.25,"type":"","binding":""},{"name":".clientdata_pixelratio","timestamp":"2024-02-21 08:54:39.227-0500","value":1.25,"type":"","binding":""},{"name":".clientdata_pixelratio","timestamp":"2024-02-21 08:54:40.794-0500","value":1.25,"type":"","binding":""},{"name":".clientdata_output_app-hot_height","timestamp":"2024-02-21 08:54:41.363-0500","value":700,"type":"","binding":""},{"name":".clientdata_output_app-hot_width","timestamp":"2024-02-21 08:54:39.816-0500","value":3000,"type":"","binding":""},{"name":".clientdata_pixelratio","timestamp":"2024-02-21 08:54:40.842-0500","value":1.25,"type":"","binding":""},{"name":".clientdata_pixelratio","timestamp":"2024-02-21 08:54:39.258-0500","value":1.25,"type":"","binding":""},{"name":".clientdata_pixelratio","timestamp":"2024-02-21 08:54:36.992-0500","value":1.25,"type":"","binding":""},{"name":".clientdata_pixelratio","timestamp":"2024-02-21 08:54:39.108-0500","value":1.25,"type":"","binding":""},{"name":".clientdata_pixelratio","timestamp":"2024-02-21 08:54:39.041-0500","value":1.25,"type":"","binding":""},{"name":".clientdata_pixelratio","timestamp":"2024-02-21 08:54:39.198-0500","value":1.25,"type":"","binding":""},{"name":".clientdata_pixelratio","timestamp":"2024-02-21 08:54:37.274-0500","value":1.25,"type":"","binding":""},{"name":".clientdata_output_app-hot_width","timestamp":"2024-02-21 08:54:41.363-0500","value":3000,"type":"","binding":""},{"name":".clientdata_pixelratio","timestamp":"2024-02-21 08:54:39.024-0500","value":1.25,"type":"","binding":""},{"name":".clientdata_pixelratio","timestamp":"2024-02-21 08:54:39.209-0500","value":1.25,"type":"","binding":""},{"name":".clientdata_pixelratio","timestamp":"2024-02-21 08:54:39.275-0500","value":1.25,"type":"","binding":""},{"name":".clientdata_output_app-hot_height","timestamp":"2024-02-21 08:54:37.778-0500","value":700,"type":"","binding":""},{"name":".clientdata_pixelratio","timestamp":"2024-02-21 08:54:39.292-0500","value":1.25,"type":"","binding":""},{"name":".clientdata_pixelratio","timestamp":"2024-02-21 08:54:39.164-0500","value":1.25,"type":"","binding":""},{"name":"HandsontableCopyPaste","timestamp":"2024-02-21 08:54:30.692-0500","value":" ","type":"","binding":"shiny.textareaInput"},{"name":".clientdata_pixelratio","timestamp":"2024-02-21 08:54:36.964-0500","value":1.25,"type":"","binding":""},{"name":".clientdata_pixelratio","timestamp":"2024-02-21 08:54:37.033-0500","value":1.25,"type":"","binding":""},{"name":".clientdata_pixelratio","timestamp":"2024-02-21 08:54:39.174-0500","value":1.25,"type":"","binding":""},{"name":".clientdata_pixelratio","timestamp":"2024-02-21 08:54:39.242-0500","value":1.25,"type":"","binding":""},{"name":".clientdata_output_app-hot_height","timestamp":"2024-02-21 08:54:39.816-0500","value":700,"type":"","binding":""},{"name":".clientdata_pixelratio","timestamp":"2024-02-21 08:54:37.069-0500","value":1.25,"type":"","binding":""},{"name":".clientdata_pixelratio","timestamp":"2024-02-21 08:54:40.776-0500","value":1.25,"type":"","binding":""},{"name":".clientdata_pixelratio","timestamp":"2024-02-21 08:54:40.862-0500","value":1.25,"type":"","binding":""},{"name":".clientdata_pixelratio","timestamp":"2024-02-21 08:54:40.825-0500","value":1.25,"type":"","binding":""},{"name":".clientdata_pixelratio","timestamp":"2024-02-21 08:54:39.077-0500","value":1.25,"type":"","binding":""},{"name":".clientdata_output_app-hot_width","timestamp":"2024-02-21 08:54:37.778-0500","value":3000,"type":"","binding":""},{"name":".clientdata_pixelratio","timestamp":"2024-02-21 08:54:37.112-0500","value":1.25,"type":"","binding":""},{"name":".clientdata_pixelratio","timestamp":"2024-02-21 08:54:40.808-0500","value":1.25,"type":"","binding":""},{"name":".clientdata_output_app-hot_height","timestamp":"2024-02-21 08:54:30.703-0500","value":700,"type":"","binding":""},{"name":".clientdata_pixelratio","timestamp":"2024-02-21 08:54:39.094-0500","value":1.25,"type":"","binding":""},{"name":".clientdata_output_app-hot_width","timestamp":"2024-02-21 08:54:30.703-0500","value":3000,"type":"","binding":""},{"name":".clientdata_pixelratio","timestamp":"2024-02-21 08:54:39.310-0500","value":1.25,"type":"","binding":""},{"name":".clientdata_pixelratio","timestamp":"2024-02-21 08:54:39.143-0500","value":1.25,"type":"","binding":""}],"session":[{"app":"police-maintenance","user":"asadowsk","server_connected":"2024-02-21 08:54:30.610-0500","sessionid":"c2ba5ca238af8dea81649a2398568edf","server_disconnected":"2024-02-21 08:55:09.203-0500","user_agent":"Mozilla/5.0 (Windows NT 10.0; Win64; x64) AppleWebKit/537.36 (KHTML, like Gecko) RStudio/2023.06.1+524 Chrome/110.0.5481.208 Electron/23.3.0 Safari/537.36","screen_res":"2560x1440","browser_res":"1066x279","pixel_ratio":1.25,"browser_connected":"2024-02-21 08:54:30.688-0500"}]}
