{"inputs":[{"name":".clientdata_output_app-hot_height","timestamp":"2024-02-21 11:41:21.277-0500","value":700,"type":"","binding":""},{"name":".clientdata_output_app-hot_width","timestamp":"2024-02-21 11:41:21.277-0500","value":2405,"type":"","binding":""}],"outputs":[{"name":"app-text","timestamp":"2024-02-21 11:41:21.222-0500","binding":"shiny.htmlOutput"},{"name":"app-hot","timestamp":"2024-02-21 11:41:21.223-0500","binding":"rhandsontable"}],"session":[{"app":"police-maintenance","user":"asadowsk","server_connected":"2024-02-21 11:41:21.163-0500","sessionid":"e6e482197c2935f82249300785e57754","server_disconnected":"2024-02-21 11:41:37.826-0500","user_agent":"Mozilla/5.0 (Windows NT 10.0; Win64; x64) AppleWebKit/537.36 (KHTML, like Gecko) Chrome/121.0.0.0 Safari/537.36 Edg/121.0.0.0","screen_res":"2560x1440","browser_res":"2512x1318","pixel_ratio":1,"browser_connected":"2024-02-21 11:41:21.190-0500"}]}
