{"inputs":[{"name":".clientdata_output_app-hot_width","timestamp":"2024-02-21 11:37:44.558-0500","value":2315,"type":"","binding":""},{"name":".clientdata_output_app-hot_height","timestamp":"2024-02-21 11:37:44.558-0500","value":700,"type":"","binding":""}],"outputs":[{"name":"app-text","timestamp":"2024-02-21 11:37:44.511-0500","binding":"shiny.htmlOutput"},{"name":"app-hot","timestamp":"2024-02-21 11:37:44.511-0500","binding":"rhandsontable"}],"session":[{"app":"police-maintenance","user":"asadowsk","server_connected":"2024-02-21 11:37:44.450-0500","sessionid":"a1e744c5041da38abe0993fecf55b134","server_disconnected":"2024-02-21 11:37:57.144-0500","user_agent":"Mozilla/5.0 (Windows NT 10.0; Win64; x64) AppleWebKit/537.36 (KHTML, like Gecko) Chrome/121.0.0.0 Safari/537.36 Edg/121.0.0.0","screen_res":"2560x1440","browser_res":"2512x1318","pixel_ratio":1,"browser_connected":"2024-02-21 11:37:44.476-0500"}]}
